mwutsdz/__init__.py
mwutsdz/core.py
mwutsdz-0.1.1.dist-info/LICENSE
mwutsdz-0.1.1.dist-info/METADATA
mwutsdz-0.1.1.dist-info/WHEEL
mwutsdz-0.1.1.dist-info/top_level.txt
mwutsdz-0.1.1.dist-info/RECORD
