Metadata-Version: 2.1
Name: mwutsdz
Version: 0.1.1
Summary: MWUT-SDZ: Détection automatique de knee point dans les données de cycle de batteries
Home-page: https://github.com/toncompte/mwutsdz
Author: Ton Nom
Author-email: ton.email@example.com
Classifier: Programming Language :: Python :: 3
Classifier: License :: OSI Approved :: MIT License
Classifier: Operating System :: OS Independent
Requires-Python: >=3.7
License-File: LICENSE
Requires-Dist: numpy
Requires-Dist: scipy
Requires-Dist: scikit-learn
Requires-Dist: pandas
Requires-Dist: matplotlib
